bgdist/Binomialdistribution.py
bgdist/Gaussiandistribution.py
bgdist/Generaldistribution.py
bgdist/__init__.py
bgdist-1.1.dist-info/DESCRIPTION.rst
bgdist-1.1.dist-info/METADATA
bgdist-1.1.dist-info/RECORD
bgdist-1.1.dist-info/WHEEL
bgdist-1.1.dist-info/metadata.json
bgdist-1.1.dist-info/top_level.txt
