Metadata-Version: 2.0
Name: bgdist
Version: 1.1
Summary: A package for Gaussian & Binomial distributions
Home-page: UNKNOWN
Author: Tapajyoti Deb
Author-email: tapajyotideb@gmail.com
License: UNKNOWN
Platform: UNKNOWN
